{
	"mask_count": 7,
	"replies": {
		"HAPPY": [
			"You think that's funny!?!",
		],
		"NEUTRAL": [
			"Cold as ice, huh?",
		],
		"SAD": [
			"You look sad...",
		],
	},
	"dialog": [
		{
			"wait_time": 0.5,
		},
		{
			"target_emotion": "HAPPY",
			"displayed_emotion": "HAPPY",
			"text": "Hi! Are you happy to see me?",
		},
		{
			"is_player": true,
			"text": "Hey!",
		},
		{
			"target_emotion": "SAD",
			"displayed_emotion": "SAD",
			"text": "My whole family just died in a car crash.....",
			"wait_time": 5.0
		},
		{
			"displayed_emotion": "HAPPY",
			"text": "I inherited a [b]TON[/b] of money, though..."
		},
	],
}
